{"fridge":{"Coins_per_success":1000,"Average_coins":960,"Avg._net_gain":400,"Death_rate":"4%"},"air":{"Coins_per_success":1000,"Average_coins":960,"Avg._net_gain":560,"Death_rate":"4%"},"area51":{"Coins_per_success":750,"Average_coins":450,"Avg._net_gain":-3550,"Death_rate":"40%"},"attic":{"Coins_per_success":450,"Average_coins":439,"Avg._net_gain":189,"Death_rate":"2.5%"},"bank":{"Coins_per_success":600,"Average_coins":360,"Avg._net_gain":-3640,"Death_rate":"40%"},"bed":{"Coins_per_success":175,"Average_coins":172,"Avg._net_gain":-29,"Death_rate":"2%"},"bus":{"Coins_per_success":150,"Average_coins":150,"Avg._net_gain":150,"Death_rate":"0%"},"bushes":{"Coins_per_success":425,"Average_coins":419,"Avg._net_gain":269,"Death_rate":"1.5%"},"car":{"Coins_per_success":0,"Average_coins":0,"Avg._net_gain":0,"Death_rate":"0%"},"coat":{"Coins_per_success":375,"Average_coins":375,"Avg._net_gain":375,"Death_rate":"0%"},"couch":{"Coins_per_success":325,"Average_coins":322,"Avg._net_gain":222,"Death_rate":"1%"},"discord":{"Coins_per_success":250,"Average_coins":245,"Avg._net_gain":45,"Death_rate":"2%"},"dog":{"Coins_per_success":500,"Average_coins":480,"Avg._net_gain":80,"Death_rate":"4%"},"dresser":{"Coins_per_success":375,"Average_coins":375,"Avg._net_gain":375,"Death_rate":"0%"},"dumpster":{"Coins_per_success":250,"Average_coins":238,"Avg._net_gain":-263,"Death_rate":"5%"},"glovebox":{"Coins_per_success":400,"Average_coins":396,"Avg._net_gain":296,"Death_rate":"1%"},"grass":{"Coins_per_success":200,"Average_coins":200,"Avg._net_gain":200,"Death_rate":"0%"},"hospital":{"Coins_per_success":500,"Average_coins":425,"Avg._net_gain":-1075,"Death_rate":"15%"},"laundromat":{"Coins_per_success":175,"Average_coins":175,"Avg._net_gain":175,"Death_rate":"0%"},"mailbox":{"Coins_per_success":250,"Average_coins":250,"Avg._net_gain":250,"Death_rate":"0%"},"pantry":{"Coins_per_success":250,"Average_coins":250,"Avg._net_gain":250,"Death_rate":"0%"},"pocket":{"Coins_per_success":125,"Average_coins":125,"Avg._net_gain":125,"Death_rate":"0%"},"purse":{"Coins_per_success":750,"Average_coins":450,"Avg._net_gain":-3550,"Death_rate":"40%"},"sewer":{"Coins_per_success":600,"Average_coins":510,"Avg._net_gain":-990,"Death_rate":"15%"},"shoe":{"Coins_per_success":250,"Average_coins":250,"Avg._net_gain":250,"Death_rate":"0%"},"sink":{"Coins_per_success":50,"Average_coins":50,"Avg._net_gain":50,"Death_rate":"0%"},"street":{"Coins_per_success":375,"Average_coins":350,"Avg._net_gain":-317,"Death_rate":"7%"},"tree":{"Coins_per_success":550,"Average_coins":528,"Avg._net_gain":128,"Death_rate":"4%"},"uber":{"Coins_per_success":485,"Average_coins":478,"Avg._net_gain":328,"Death_rate":"1.5%"},"vacuum":{"Coins_per_success":0,"Average_coins":0,"Avg._net_gain":0,"Death_rate":0}}
